circulation_import/__init__.py
circulation_import/__main__.py
circulation_import/cli.py
circulation_import/client/cli.py
circulation_import/client/client.py
circulation_import/client/configuration.py
circulation_import/configuration.py
circulation_import/errors.py
circulation_import/hash.py
circulation_import/metadata/configuration.py
circulation_import/metadata/serialization.py
circulation_import/server/cli.py
circulation_import/server/configuration.py
circulation_import/server/importer.py
circulation_import/server/server.py
circulation_import/server/storage.py
circulation_import/sftp/client.py
circulation_import/sftp/configuration.py
circulation_import/storage/configuration.py
circulation_import/storage/model.py
circulation_import/storage/storage.py
circulation_import/utils.py
circulation_import-0.0.1.dist-info/LICENSE
circulation_import-0.0.1.dist-info/WHEEL
circulation_import-0.0.1.dist-info/METADATA
circulation_import-0.0.1.dist-info/RECORD
