Metadata-Version: 2.1
Name: circulation-import
Version: 0.0.1
Summary: Set of tools facilitating the process of importing book collections into SimplyE's Circulation Manager by using SFTP protocol
Home-page: https://github.com/vbessonov/circulation-import
License: MIT
Author: Viacheslav Bessonov
Author-email: viacheslav.bessonov@hilbertteam.com
Requires-Python: >=3.7,<4.0
Classifier: License :: OSI Approved :: MIT License
Classifier: Programming Language :: Python :: 3
Classifier: Programming Language :: Python :: 3.7
Classifier: Programming Language :: Python :: 3.8
Requires-Dist: attrs (>=20.1.0,<21.0.0)
Requires-Dist: click (>=7.1.2,<8.0.0)
Requires-Dist: paramiko (>=2.7.2,<3.0.0)
Requires-Dist: ruamel.yaml (>=0.16.10,<0.17.0)
Requires-Dist: sqlalchemy (>=1.3.19,<2.0.0)
Requires-Dist: sqlalchemy-repr (>=0.0.2,<0.0.3)
Requires-Dist: typing-inspect (>=0.6.0,<0.7.0)
Requires-Dist: watchdog (>=0.10.3,<0.11.0)
Project-URL: Repository, https://github.com/vbessonov/circulation-import
